bookiesports/__init__.py
bookiesports/cli.py
bookiesports/datestring.py
bookiesports/exceptions.py
bookiesports/log.py
bookiesports/normalize.py
bookiesports/bookiesports/alice/index.yaml
bookiesports/bookiesports/alice/AmericanFootball/README.md
bookiesports/bookiesports/alice/AmericanFootball/index.yaml
bookiesports/bookiesports/alice/AmericanFootball/NFL#RegSeas/index.yaml
bookiesports/bookiesports/alice/AmericanFootball/bettingmarketgroups/NFL_HCP_1.yaml
bookiesports/bookiesports/alice/AmericanFootball/bettingmarketgroups/NFL_ML_1.yaml
bookiesports/bookiesports/alice/AmericanFootball/bettingmarketgroups/NFL_OU_1.yaml
bookiesports/bookiesports/alice/AmericanFootball/participants/NFL_Teams_2021-22.yaml
bookiesports/bookiesports/alice/AmericanFootball/rules/R_NFL_HCP_1.yaml
bookiesports/bookiesports/alice/AmericanFootball/rules/R_NFL_ML_1.yaml
bookiesports/bookiesports/alice/AmericanFootball/rules/R_NFL_OU_1.yaml
bookiesports/bookiesports/alice/Baseball/README.md
bookiesports/bookiesports/alice/Baseball/index.yaml
bookiesports/bookiesports/alice/Baseball/MLB#RegSeas/index.yaml
bookiesports/bookiesports/alice/Baseball/bettingmarketgroups/MLB_HCP_1.yaml
bookiesports/bookiesports/alice/Baseball/bettingmarketgroups/MLB_ML_1.yaml
bookiesports/bookiesports/alice/Baseball/bettingmarketgroups/MLB_OU_1.yaml
bookiesports/bookiesports/alice/Baseball/participants/MLB_Teams_2021-22.yaml
bookiesports/bookiesports/alice/Baseball/rules/R_MLB_HCP_1.yaml
bookiesports/bookiesports/alice/Baseball/rules/R_MLB_ML_1.yaml
bookiesports/bookiesports/alice/Baseball/rules/R_MLB_OU_1.yaml
bookiesports/bookiesports/alice/Basketball/README.md
bookiesports/bookiesports/alice/Basketball/index.yaml
bookiesports/bookiesports/alice/Basketball/NBA#RegSeas/index.yaml
bookiesports/bookiesports/alice/Basketball/bettingmarketgroups/NBA_HCP_1.yaml
bookiesports/bookiesports/alice/Basketball/bettingmarketgroups/NBA_ML_1.yaml
bookiesports/bookiesports/alice/Basketball/bettingmarketgroups/NBA_OU_1.yaml
bookiesports-0.4.18.dist-info/LICENSE.txt
bookiesports-0.4.18.dist-info/METADATA
bookiesports-0.4.18.dist-info/WHEEL
bookiesports-0.4.18.dist-info/entry_points.txt
bookiesports-0.4.18.dist-info/top_level.txt
bookiesports-0.4.18.dist-info/RECORD
