Metadata-Version: 2.1
Name: bookiesports
Version: 0.4.18
Summary: Sports module for bookied
Home-page: http://pbsa.info
Author: Peerplays Community
Maintainer: Peerplays Community
License: UNKNOWN
Download-URL: https://github.com/pbsa/bookiesports/tarball/0.4.18
Keywords: peerplays,bos
Platform: UNKNOWN
Classifier: License :: OSI Approved :: GNU General Public License v3 (GPLv3)
Classifier: Operating System :: OS Independent
Classifier: Programming Language :: Python :: 3
Classifier: Development Status :: 3 - Alpha
Classifier: Intended Audience :: Developers
Requires-Dist: peerplays
Requires-Dist: bos-sync
Requires-Dist: pyyaml
Requires-Dist: jsonschema
Requires-Dist: colorlog
Requires-Dist: strict-rfc3339
